pelican/plugins/pelican_mini_wiki/__init__.py
pelican/plugins/pelican_mini_wiki/pelican_mini_wiki.py
pelican/plugins/pelican_mini_wiki/test_pelican_mini_wiki.py
pelican/themes/simple/templates/wiki_base.html
pelican_mini_wiki-0.0.5.dist-info/LICENSE.md
pelican_mini_wiki-0.0.5.dist-info/METADATA
pelican_mini_wiki-0.0.5.dist-info/WHEEL
pelican_mini_wiki-0.0.5.dist-info/top_level.txt
pelican_mini_wiki-0.0.5.dist-info/RECORD
