Metadata-Version: 2.1
Name: pelican-mini-wiki
Version: 0.0.5
Summary: Pelican Mini Wiki allows you to add a minimal wiki to any Pelican theme and website.
Author-email: Michael Haslam <hreikin@gmail.com>
License: 
Project-URL: Homepage, https://github.com/hreikin/pelican-mini-wiki
Project-URL: Bug Tracker, https://github.com/hreikin/pelican-mini-wiki/issues
Classifier: Development Status :: 4 - Beta
Classifier: Environment :: Console
Classifier: Framework :: Pelican
Classifier: Framework :: Pelican :: Plugins
Classifier: Intended Audience :: End Users/Desktop
Classifier: License :: OSI Approved :: MIT License
Classifier: Operating System :: OS Independent
Classifier: Programming Language :: Python :: 3
Classifier: Topic :: Internet :: WWW/HTTP
Classifier: Topic :: Software Development :: Libraries :: Python Modules
Requires-Python: >=3.7
License-File: LICENSE.md
